LICENSE
MANIFEST.in
README.md
setup.cfg
setup.py
django_bundles/__init__.py
django_bundles/core.py
django_bundles/models.py
django_bundles/views.py
django_bundles.egg-info/PKG-INFO
django_bundles.egg-info/SOURCES.txt
django_bundles.egg-info/dependency_links.txt
django_bundles.egg-info/top_level.txt
django_bundles/conf/__init__.py
django_bundles/conf/bundles_settings.py
django_bundles/conf/default_settings.py
django_bundles/management/__init__.py
django_bundles/management/commands/__init__.py
django_bundles/management/commands/create_bundle_manifests.py
django_bundles/management/commands/create_bundles.py
django_bundles/management/commands/lint_bundles.py
django_bundles/management/commands/remove_bundles.py
django_bundles/management/commands/watch_bundles.py
django_bundles/processors/__init__.py
django_bundles/processors/base.py
django_bundles/processors/django_template.py
django_bundles/templatetags/__init__.py
django_bundles/templatetags/django_bundles_tags.py
django_bundles/tests/__init__.py
django_bundles/tests/conf.py
django_bundles/tests/core.py
django_bundles/tests/templatetags.py
django_bundles/tests/utils/__init__.py
django_bundles/tests/utils/files.py
django_bundles/tests/utils/processes.py
django_bundles/utils/__init__.py
django_bundles/utils/files.py
django_bundles/utils/processes.py