Metadata-Version: 1.0
Name: django-bundles
Version: 0.6.6
Summary: Another Django media bundler
Home-page: https://github.com/sdcooke/django_bundles
Author: Sam Cooke
Author-email: sam.cooke@xylate.com
License: MIT license, see LICENSE file
Platform: UNKNOWN
